git_taxbreak/__init__.py
git_taxbreak/cmd.py
git_taxbreak/modules/__init__.py
git_taxbreak/modules/argument_parser.py
git_taxbreak/modules/artifacts_collector.py
git_taxbreak/modules/writter.py
git_taxbreak-0.1.0.dist-info/entry_points.txt
git_taxbreak-0.1.0.dist-info/LICENSE
git_taxbreak-0.1.0.dist-info/WHEEL
git_taxbreak-0.1.0.dist-info/METADATA
git_taxbreak-0.1.0.dist-info/RECORD
