Metadata-Version: 2.1
Name: git-taxbreak
Version: 0.1.0
Summary: Tool for collect artifacts from git for register creative work
Home-page: https://github.com/kamil1b/git-taxbreak
License: MIT
Keywords: git,taxbreak,tool
Author: Luczak Kamil
Author-email: kamilluczak@luczakweb.com
Requires-Python: >=3.5
Classifier: Development Status :: 3 Alpha
Classifier: Intended Audience :: Developers
Classifier: License :: OSI Approved :: MIT License
Classifier: Operating System :: POSIX
Classifier: Programming Language :: Python :: 3
Classifier: Programming Language :: Python :: 3.5
Classifier: Programming Language :: Python :: 3.6
Classifier: Programming Language :: Python :: 3.7
Classifier: Programming Language :: Python :: 3.8
Classifier: Topic :: Utilities
Requires-Dist: gitpython (>=3,<4)
Requires-Dist: pre-commit (>=1.20,<2.0)
Project-URL: Repository, https://github.com/kamil1b/git-taxbreak
